kafka_mocha/__init__.py
kafka_mocha/core/__init__.py
kafka_mocha/core/buffer_handler.py
kafka_mocha/core/kafka_simulator.py
kafka_mocha/core/kconsumer.py
kafka_mocha/core/kproducer.py
kafka_mocha/core/ticking_thread.py
kafka_mocha/exceptions/__init__.py
kafka_mocha/klogger.py
kafka_mocha/models/__init__.py
kafka_mocha/models/kmodels.py
kafka_mocha/models/ktypes.py
kafka_mocha/models/signals.py
kafka_mocha/renderers.py
kafka_mocha/schema_registry/__init__.py
kafka_mocha/schema_registry/exceptions.py
kafka_mocha/schema_registry/mock_schema_registry_client.py
kafka_mocha/schema_registry/schema_registry_client.py
kafka_mocha/schema_registry/srlogger.py
kafka_mocha/schema_registry/wrappers.py
kafka_mocha/templates/favicon.ico
kafka_mocha/templates/messages.csv.jinja
kafka_mocha/templates/messages.html.jinja
kafka_mocha/templates/messages.json.jinja
kafka_mocha/utils.py
kafka_mocha/wrappers.py
kafka_mocha-2.2.1.dist-info/METADATA
kafka_mocha-2.2.1.dist-info/WHEEL
kafka_mocha-2.2.1.dist-info/licenses/LICENSE
kafka_mocha-2.2.1.dist-info/licenses/LICENSE.APACHE
kafka_mocha-2.2.1.dist-info/RECORD
