Metadata-Version: 2.4
Name: kafka-mocha
Version: 2.2.1
Summary: A Kafka mock library that is designed to be used in integration tests for applications using librdkafka.
License: MIT
License-File: LICENSE
License-File: LICENSE.APACHE
Author: and-ratajski
Author-email: and.ratajski@effiware.com
Requires-Python: >=3.11,<4.0
Classifier: License :: OSI Approved :: MIT License
Classifier: Operating System :: OS Independent
Classifier: Programming Language :: Python :: 3
Classifier: Programming Language :: Python :: 3.11
Classifier: Programming Language :: Python :: 3.12
Classifier: Programming Language :: Python :: 3.13
Classifier: Programming Language :: Python :: 3.14
Requires-Dist: Jinja2 (>=3.1.5,<4.0.0)
Requires-Dist: confluent-kafka (>=2.4.0,<3.0.0,!=2.6.2,!=2.8.1,<=2.10.0)
Requires-Dist: jsonschema (>=4.24.0,<5.0.0)
Requires-Dist: referencing (>=0.36.2,<0.37.0)
Project-URL: Homepage, https://github.com/Effiware/kafka-mocha/wiki
Project-URL: Repository, https://github.com/Effiware/kafka-mocha
